_picosat.so
picosat.py
pyPicosat-960.dev1510262107.dist-info/DESCRIPTION.rst
pyPicosat-960.dev1510262107.dist-info/METADATA
pyPicosat-960.dev1510262107.dist-info/RECORD
pyPicosat-960.dev1510262107.dist-info/WHEEL
pyPicosat-960.dev1510262107.dist-info/metadata.json
pyPicosat-960.dev1510262107.dist-info/top_level.txt
