Metadata-Version: 2.0
Name: pyPicosat
Version: 960.dev1510262107
Summary: Picosat SAT-Solver Wrapper
Home-page: https://github.com/pysmt/pyPicoSAT/
Author: PySMT Team
Author-email: info@pysmt.org
License: BSD
Platform: UNKNOWN
Classifier: Programming Language :: Python
Classifier: Programming Language :: Python :: 3
Classifier: Development Status :: 4 - Beta
Classifier: Intended Audience :: Developers
Classifier: Topic :: Software Development :: Libraries :: Python Modules
